py_stylus_ui/__init__.py
py_stylus_ui/py_stylus_ui.py
py_stylus_ui-0.1.1.dist-info/LICENSE
py_stylus_ui-0.1.1.dist-info/METADATA
py_stylus_ui-0.1.1.dist-info/WHEEL
py_stylus_ui-0.1.1.dist-info/entry_points.txt
py_stylus_ui-0.1.1.dist-info/top_level.txt
py_stylus_ui-0.1.1.dist-info/RECORD
